README.md
setup.cfg
setup.py
deluca/lung/__init__.py
deluca/lung/core.py
deluca/lung/controllers/__init__.py
deluca/lung/controllers/_bang_bang.py
deluca/lung/controllers/_expiratory.py
deluca/lung/controllers/_impulse.py
deluca/lung/controllers/_jax_pid.py
deluca/lung/controllers/_periodic_impulse.py
deluca/lung/controllers/_pid.py
deluca/lung/controllers/_predestined.py
deluca/lung/controllers/_residual_explorer.py
deluca/lung/devices/__init__.py
deluca/lung/devices/base.py
deluca/lung/devices/hal.py
deluca/lung/devices/pins.py
deluca/lung/devices/sensors.py
deluca/lung/devices/valves.py
deluca/lung/environments/__init__.py
deluca/lung/environments/_balloon_lung.py
deluca/lung/environments/_cnn.py
deluca/lung/environments/_delay_lung.py
deluca/lung/environments/_double_comp_lung.py
deluca/lung/environments/_double_comp_lung_pid.py
deluca/lung/environments/_linear.py
deluca/lung/environments/_lstm.py
deluca/lung/environments/_mlp.py
deluca/lung/environments/_physical_lung.py
deluca/lung/environments/_single_comp_lung.py
deluca/lung/environments/_single_comp_lung_pid.py
deluca/lung/environments/_stitched_sim.py
deluca/lung/experimental/__init__.py
deluca/lung/experimental/controllers/__init__.py
deluca/lung/experimental/controllers/_clipped_adv_deep.py
deluca/lung/experimental/controllers/_clipped_deep.py
deluca/lung/experimental/controllers/_deep.py
deluca/lung/experimental/controllers/_deep_pid_residual.py
deluca/lung/experimental/controllers/_deep_pid_residual_clipped.py
deluca/lung/experimental/controllers/_ibonus.py
deluca/lung/experimental/controllers/_mpc.py
deluca/lung/experimental/controllers/_pid_correction.py
deluca/lung/experimental/environments/__init__.py
deluca/lung/experimental/environments/_old_stitched_sim.py
deluca/lung/utils/__init__.py
deluca/lung/utils/core.py
deluca/lung/utils/data/alpha_dropout.py
deluca/lung/utils/data/analyzer.py
deluca/lung/utils/data/dataset.py
deluca/lung/utils/data/featurizer.py
deluca/lung/utils/data/jax_data.py
deluca_lung.egg-info/PKG-INFO
deluca_lung.egg-info/SOURCES.txt
deluca_lung.egg-info/dependency_links.txt
deluca_lung.egg-info/requires.txt
deluca_lung.egg-info/top_level.txt