Metadata-Version: 2.1
Name: deluca-lung
Version: 0.0.5
Summary: UNKNOWN
Home-page: https://github.com/MinRegret/deluca-lung
Author: Google AI Princeton
Author-email: dsuo@google.com
License: Apache License
Keywords: differentiable,control algorithms,reinforcement learning
Platform: UNKNOWN
Classifier: Programming Language :: Python :: 3
Classifier: License :: OSI Approved :: Apache Software License
Classifier: Operating System :: OS Independent
Classifier: Development Status :: 3 - Alpha
